depdive/__init__.py
depdive/__main__.py
depdive/code_review.py
depdive/code_review_checker.py
depdive/common.py
depdive/py.typed
depdive/registry_diff.py
depdive/repository_diff.py
depdive-0.0.42.dist-info/entry_points.txt
depdive-0.0.42.dist-info/LICENSE
depdive-0.0.42.dist-info/WHEEL
depdive-0.0.42.dist-info/METADATA
depdive-0.0.42.dist-info/RECORD
