Metadata-Version: 2.1
Name: depdive
Version: 0.0.42
Summary: Performs security checks for a dependency update
Home-page: https://github.com/nasifimtiazohi/depdive
License: MIT
Author: Nasif Imtiaz
Author-email: nasifimtiaz88@gmail.com
Requires-Python: >=3.9,<4.0
Classifier: License :: OSI Approved :: MIT License
Classifier: Programming Language :: Python :: 3
Classifier: Programming Language :: Python :: 3.9
Classifier: Programming Language :: Python :: 3.10
Classifier: Programming Language :: Python :: 3.6
Classifier: Programming Language :: Python :: 3.7
Classifier: Programming Language :: Python :: 3.8
Classifier: Programming Language :: Python :: 3.9
Requires-Dist: PyGithub (>=1.55,<2.0)
Requires-Dist: PyYAML (>=5.4.1,<6.0.0)
Requires-Dist: click (>=8.0.0,<9.0.0)
Requires-Dist: package-locator (>=0.4.4,<0.5.0)
Requires-Dist: rich (>=10.3.0,<11.0.0)
Requires-Dist: version-differ (>=0.3.14,<0.4.0)
Project-URL: Documentation, https://depdive.readthedocs.io
Project-URL: Repository, https://github.com/nasifimtiazohi/depdive
